quickbar/README.md
quickbar/__init__.py
quickbar/__main__.py
quickbar/core.py
quickbar-0.1.1.post0.dist-info/METADATA
quickbar-0.1.1.post0.dist-info/WHEEL
quickbar-0.1.1.post0.dist-info/entry_points.txt
quickbar-0.1.1.post0.dist-info/RECORD
